Tarea1/src/probador.v
module probador (
    output reg reset, A, B, C, clock, // Declarar como reg porque son driven en el testbench
    input Bloqueo, Aguja
);


  initial begin
    // Inicialización de las señales
    reset = 1; 
    A = 0; 
    B = 0; 
    C = 0; 
    clock = 0; 
    
    // Se apaga el reset
    #5 reset = 0;
    
    // Escenario de prueba 1. Escenario Ideal.
    #4 A = 1; B = 0; //Validacion de la contrasena en base a los estados.
    #4 A = 1; B = 0; //Validacion de la contrasena en base a los estados.
    #4 A = 1; B = 0; //Validacion de la contrasena en base a los estados.
    #4 A = 1; B = 1; //Validacion de la contrasena en base a los estados.
    #4 A = 1; B = 0; //Validacion de la contrasena en base a los estados.
    #4 A = 1; B = 1; // Como la contrasena es 00111111, se busca que las
    #4 A = 1; B = 0; // ondas de los estados reflejen esos bits. Es un flop por
    #4 A = 1; B = 0; // bit. Entonces, cada flop va a tener un valor binario.
    //#10 A = 1; B = \; //Cuando los flops se comportan como la senal, es un caso de 
    //#10 A = 1; B = 1; //exito.
    
    // Funcionamiento del sensor A (llegada de carro), sensor B(contrasena) y 
    // sensor C (carro ya termino de entrar)
//
    //#85 A = 0; B = 0; C = 1;
    //#85 A = 1; B = 1; C = 0;
    //#85 A = 1; B = 0 ; C = 1;
    //#85 A = 1; C = 1;
    //#85 A = 0; C = 0;
    #100 $finish;
   
  end

  // Generar la señal de reloj
  always begin
    #1 clock = ~clock; // Cambiar el valor de la señal de reloj cada 5 unidades de tiempo
  end 

endmodule

Tarea1/Tarea1.v
module me (
    input reset, A, B, C, clock,
    output reg Bloqueo,
    output reg Aguja
);

// Variables internas
reg [7:0] state;
reg [7:0] nxt_state;
reg [7:0] last_state;

// Variables para el control del tiempo
reg [3:0] contador_tiempo = 0; // Contador de 4 bits para contar hasta 15 segundos
reg [2:0] contador = 0;

// Máquina de estados
always @(posedge clock or posedge reset) begin
    if (reset) begin
        state <= 8'b00000000; 
    end else begin
        state <= nxt_state;
    end
end

// Lógica de próximo estado
always @(*) begin
    nxt_state = state; // Por defecto, próximo estado es el mismo que el estado actual

    case(state)
       //8'b00000000: if (A == 1 && B == 0) nxt_state <= 8'b00000000;
       8'b00000000: if (A == 1 && B == 1) nxt_state <= 8'b00000001;
       8'b00000001: if (A == 1 && B == 0) nxt_state = 8'b00000010;
       8'b00000010: if (A == 1 && B == 1) nxt_state = 8'b00000101;
       8'b00000101: if (A == 1 && B == 0) nxt_state = 8'b00001010;
       8'b00001010: if (A == 1 && B == 0) nxt_state = 8'b00010100;

       

        /*default: begin
            //nxt_state = 8'b00000000; // Manejo de estado inesperado
            if (state == last_state) begin
                    contador <= contador + 1;
            end
        end*/
    endcase
    //last_state = state; // Actualizar el último estado
/*

 /*
        if (A == 0 && B == 0 && C == 1) begin
            // Si A y B son 0, y C es 1, bajar la aguja
            Aguja = 0;
        end else if (A == 1 && B == 1 && C == 0) begin
            // Si A y B son 1, y C es 0, levantar la aguja
            Aguja = 1;
        end else begin
            // En cualquier otro caso, mantener la aguja en su estado anterior
            Aguja = 0;
        end
        
        if (A == 1 && C == 1) begin
            // Si A y C son 1, encender la alarma
            Bloqueo = 1;
        end else if (A == 0 && C == 0) begin
            // Si A y C son 0, apagar la alarma
            Bloqueo = 0;
        end else begin
            // En cualquier otro caso, mantener el estado de la alarma
            Bloqueo = Bloqueo;  
        end
    end


// Incrementar el contador de tiempo en cada ciclo de reloj
always @(posedge clock) begin
    if (reset) begin
        contador_tiempo <= 0;
    end else if (contador_tiempo < 15) begin
        contador_tiempo <= contador_tiempo + 1;
    end
end

// Lógica adicional para evitar que se levante la alarma si se levanta la aguja, y viceversa
always @(posedge clock) begin
    $display("Estado actual: A=%b, B=%b, C=%b, Bloqueo=%b, Aguja=%b", A, B, C, Bloqueo, Aguja);
  */  
end

endmodule

Tarea1/src/Testbench.v
`include "probador.v"
`include "Tarea1.v"

module aguja_tb;
        // Señales de salida
    wire Bloqueo;
    wire Aguja;
    wire A;
    wire B;
    wire C;
    wire clock;
    wire reset;
    wire cont;

   // wire valid;
    
    // Generación de estímulo
    initial begin
        $dumpfile("testbench.vcd"); // Genera un archivo VCD para ver la simulación
        $dumpvars(-1, uut); // Agrega todas las variables a ser volcadas en el archivo VCD
    end

        // Instancia del módulo a testear
    me uut (
        .reset(reset),
        .A(A),
        .B(B),
        .C(C),
        .Bloqueo(Bloqueo),
        .Aguja(Aguja),
        .clock(clock)
       // .valid(valid)
    );


    probador P0 (
        .reset(reset),
        .A(A),
        .B(B),
        .C(C),
        .Bloqueo(Bloqueo),
        .Aguja(Aguja),
        .clock(clock)
       // .valid(valid)
    );
//cambio para notar push
endmodule

Tarea1/testbench.vcd
$date
	Thu Apr 11 01:13:22 2024
$end
$version
	Icarus Verilog
$end
$timescale
	1s
$end
$scope module aguja_tb $end
$scope module uut $end
$var wire 1 ! A $end
$var wire 1 " B $end
$var wire 1 # C $end
$var wire 1 $ clock $end
$var wire 1 % reset $end
$var reg 1 & Aguja $end
$var reg 1 ' Bloqueo $end
$var reg 3 ( contador [2:0] $end
$var reg 4 ) contador_tiempo [3:0] $end
$var reg 8 * nxt_state [7:0] $end
$var reg 8 + state [7:0] $end
$upscope $end
$upscope $end
$enddefinitions $end
#0
$dumpvars
b0 +
b0 *
b0 )
b0 (
x'
x&
1%
0$
0#
0"
0!
$end
#1
1$
#2
0$
#3
1$
#4
0$
#5
1$
0%
#6
0$
#7
1$
#8
0$
#9
1$
1!
#10
0$
#11
1$
#12
0$
#13
1$
#14
0$
#15
1$
#16
0$
#17
1$
#18
0$
#19
1$
#20
0$
#21
b1 *
1$
1"
#22
0$
#23
b1 +
1$
#24
0$
#25
b10 +
b10 *
1$
0"
#26
0$
#27
1$
#28
0$
#29
b101 +
b101 *
1$
1"
#30
0$
#31
1$
#32
0$
#33
b1010 +
b10100 *
1$
0"
#34
0$
#35
b10100 +
1$
